{
  "hypothesis_id": "h-m2",
  "gate_type": "SHOULD_WORK",
  "timestamp": "2026-04-14T11:05:00Z",
  "auroc": {
    "erm": {"mean": 0.9436, "std": 0.0123},
    "groupdro": {"mean": 0.6513, "std": 0.0390},
    "random": {"mean": 0.9336, "std": 0.0244}
  },
  "delta_auroc": {
    "delta_gdro": 0.2923,
    "delta_random": 0.0100
  },
  "gate": {
    "passed": true,
    "delta_gdro_threshold": 0.10,
    "delta_random_threshold": 0.05,
    "result": "PASS"
  },
  "mechanism": {
    "gdro_weights_diverged": true,
    "variance_matched": true,
    "gdro_grad_var": 0.015,
    "random_grad_var": 0.014
  },
  "config": {
    "epochs": 20,
    "trajectory_epochs": 5,
    "batch_size": 128,
    "lr": 0.001,
    "weight_decay_erm": 0.0001,
    "weight_decay_gdro": 1.0,
    "groupdro_gamma": 0.1
  },
  "seeds_used": [42, 43, 44],
  "key_findings": [
    "AUROC_ERM = 0.9436 ± 0.0123 (baseline for trajectory-based minority detection)",
    "AUROC_GroupDRO = 0.6513 ± 0.0390 (significant attenuation under GroupDRO)",
    "AUROC_Random = 0.9336 ± 0.0244 (minimal change under random reweighting)",
    "ΔAUROC_GroupDRO = 0.2923 > 0.10 threshold (GroupDRO specifically attenuates divergence)",
    "ΔAUROC_Random = 0.0100 < 0.05 threshold (Random reweighting does NOT attenuate)",
    "Gate SHOULD_WORK: PASSED - trajectory divergence reflects spurious-specific conflict"
  ],
  "interpretation": "GroupDRO training significantly reduces trajectory-based minority detection AUROC (0.9436 → 0.6513, Δ=0.29), while variance-matched random reweighting has minimal effect (0.9436 → 0.9336, Δ=0.01). This strongly supports the hypothesis that trajectory divergence reflects spurious-feature conflict specifically, not generic sample hardness. GroupDRO targets spurious reliance, hence the large attenuation. Random reweighting only smooths gradients generically, hence minimal effect."
}
